autolyap/__init__.py
autolyap/iteration_dependent.py
autolyap/iteration_independent.py
autolyap/problemclass.py
autolyap/algorithms/__init__.py
autolyap/algorithms/accelerated_proximal_point.py
autolyap/algorithms/algorithm.py
autolyap/algorithms/chambolle_pock.py
autolyap/algorithms/davis_yin.py
autolyap/algorithms/deterministic_proxskip.py
autolyap/algorithms/douglas_rachford.py
autolyap/algorithms/extragradient.py
autolyap/algorithms/forward.py
autolyap/algorithms/gradient.py
autolyap/algorithms/gradient_with_Nesterov_like_momentum.py
autolyap/algorithms/heavy_ball.py
autolyap/algorithms/information_theoretic_exact_method.py
autolyap/algorithms/malitsky_tam_frb.py
autolyap/algorithms/nesterov_constant.py
autolyap/algorithms/nesterov_fast_gradient_method.py
autolyap/algorithms/optimized_gradient_method.py
autolyap/algorithms/proximal_point.py
autolyap/algorithms/triple_momentum.py
autolyap/algorithms/tseng_fbf.py
autolyap/utils/__init__.py
autolyap/utils/helper_functions.py
autolyap-0.1.0.dist-info/licenses/LICENSE
autolyap-0.1.0.dist-info/METADATA
autolyap-0.1.0.dist-info/WHEEL
autolyap-0.1.0.dist-info/top_level.txt
autolyap-0.1.0.dist-info/RECORD
