Metadata-Version: 2.4
Name: autolyap
Version: 0.1.0
Summary: Automatic Lyapunov analysis
Home-page: https://autolyap.github.io
Author: Manu Upadhyaya
Author-email: manu.upadhyaya.42@gmail.com
License: MIT
Project-URL: Documentation, https://autolyap.github.io/
Classifier: Programming Language :: Python :: 3
Classifier: License :: OSI Approved :: MIT License
Classifier: Topic :: Scientific/Engineering :: Mathematics
Requires-Python: >=3.9
License-File: LICENSE
Requires-Dist: numpy>=1.24
Requires-Dist: mosek>=10.0
Dynamic: author
Dynamic: author-email
Dynamic: classifier
Dynamic: description
Dynamic: description-content-type
Dynamic: home-page
Dynamic: license
Dynamic: license-file
Dynamic: project-url
Dynamic: requires-dist
Dynamic: requires-python
Dynamic: summary
